timeline_kun/__init__.py
timeline_kun/__main__.py
timeline_kun/app_previewer.py
timeline_kun/app_timer.py
timeline_kun/ble_control.py
timeline_kun/cli.py
timeline_kun/config_toml.py
timeline_kun/csv_to_timetable.py
timeline_kun/events.json
timeline_kun/events_json.py
timeline_kun/file_loader.py
timeline_kun/gui_ble_button.py
timeline_kun/gui_canvas.py
timeline_kun/gui_parts.py
timeline_kun/gui_tree.py
timeline_kun/icon_data.py
timeline_kun/sound.py
timeline_kun/svg_writer.py
timeline_kun/time_format.py
timeline_kun/timer_log.py
timeline_kun/timetable_to_csv.py
timeline_kun/trigger.py
timeline_kun/img/icon.ico
timeline_kun/img/icon.png
timeline_kun/sound/countdown3_cyan.wav
timeline_kun/sound/countdown3_lightgreen.wav
timeline_kun/sound/countdown3_orange.wav
timeline_kun-1.0.1.dist-info/METADATA
timeline_kun-1.0.1.dist-info/WHEEL
timeline_kun-1.0.1.dist-info/entry_points.txt
timeline_kun-1.0.1.dist-info/licenses/LICENSE
timeline_kun-1.0.1.dist-info/RECORD
