Metadata-Version: 2.4
Name: timeline-kun
Version: 1.0.1
Summary: An integrated graphical interface tool for planning and executing experimental protocols.
Project-URL: Homepage, https://github.com/nishimura5/timeline_kun
Project-URL: Repository, https://github.com/nishimura5/timeline_kun
Author: Eigo Nishimura
License:                     GNU AFFERO GENERAL PUBLIC LICENSE
License-File: LICENSE
Keywords: GUI,experiment,protocol,timeline,timer
Requires-Python: >=3.11
Requires-Dist: bleak>=0.22.3
Requires-Dist: sounddevice>=0.5.1
Requires-Dist: soundfile>=0.13.1
Requires-Dist: ttkthemes>=3.2.2
